pytomation/__init__.py
pytomation/__main__.py
pytomation/action.py
pytomation/action_inventory.py
pytomation/action_metadata.py
pytomation/action_wrapper/__init__.py
pytomation/action_wrapper/depends_on/__init__.py
pytomation/action_wrapper/depends_on/executor.py
pytomation/action_wrapper/profile/__init__.py
pytomation/action_wrapper/util.py
pytomation/app.py
pytomation/cli/__init__.py
pytomation/cli/action_command.py
pytomation/cli/app_factory.py
pytomation/cli/arguments.py
pytomation/cli/verify_command.py
pytomation/context.py
pytomation/discovery/__init__.py
pytomation/discovery/file_discover.py
pytomation/errors.py
pytomation/file_builder/__init__.py
pytomation/file_builder/deprecated
pytomation/file_builder/file_builder.py
pytomation/file_builder/local_file_builder.py
pytomation/module.py
pytomation/module_graph.py
pytomation/plugin.py
pytomation/profile.py
pytomation/utils/__init__.py
pytomation/utils/command.py
pytomation-0.0.7.dist-info/METADATA
pytomation-0.0.7.dist-info/WHEEL
pytomation-0.0.7.dist-info/entry_points.txt
pytomation-0.0.7.dist-info/RECORD
