Metadata-Version: 2.1
Name: pytomation
Version: 0.0.7
Summary: An advanced, fully hackable automation library written in Python
License: GPL-3.0-or-later
Author: Aran Moncusí Ramírez
Author-email: aran@digitalpoet.info
Requires-Python: >=3.12,<4.0
Classifier: License :: OSI Approved :: GNU General Public License v3 or later (GPLv3+)
Classifier: Programming Language :: Python :: 3
Classifier: Programming Language :: Python :: 3.12
